azpype/__init__.py
azpype/logging_config.py
azpype/resource_paths.py
azpype/retry.py
azpype/setup.py
azpype/validators.py
azpype/assets/bin/azcopy_darwin_amd64_10.18.1/NOTICE.txt
azpype/assets/bin/azcopy_darwin_amd64_10.18.1/azcopy
azpype/assets/bin/azcopy_linux_amd64_10.18.1/NOTICE.txt
azpype/assets/bin/azcopy_linux_amd64_10.18.1/azcopy
azpype/assets/bin/azcopy_linux_arm64_10.18.1/NOTICE.txt
azpype/assets/bin/azcopy_linux_arm64_10.18.1/azcopy
azpype/assets/bin/azcopy_windows_amd64_10.18.1/NOTICE.txt
azpype/assets/bin/azcopy_windows_amd64_10.18.1/azcopy.exe
azpype/assets/config_templates/copy_config.yaml
azpype/commands/__init__.py
azpype/commands/base_command.py
azpype/commands/copy.py
azpype/commands/jobs.py
azpype/commands/stdout_parser.py
azpype-0.5.4.dist-info/licenses/LICENSE
azpype-0.5.4.dist-info/licenses/NOTICE.txt
azpype-0.5.4.dist-info/METADATA
azpype-0.5.4.dist-info/WHEEL
azpype-0.5.4.dist-info/top_level.txt
azpype-0.5.4.dist-info/RECORD
