Metadata-Version: 2.4
Name: azpype
Version: 0.5.4
Summary: A native Python interface wrapping AzCopy for bulk data transfer to and from Azure Blob Storage.
Home-page: https://github.com/yusuf-jkhan1/azpype
Author: Yusuf Khan
License: MIT
Classifier: License :: OSI Approved :: MIT License
Classifier: Programming Language :: Python
Classifier: Programming Language :: Python :: 3
License-File: LICENSE
License-File: NOTICE.txt
Requires-Dist: appnope==0.1.3
Requires-Dist: asttokens==2.2.1
Requires-Dist: backcall==0.2.0
Requires-Dist: cffi==1.17.1
Requires-Dist: click==8.1.3
Requires-Dist: comm==0.1.3
Requires-Dist: cryptography==40.0.2
Requires-Dist: debugpy==1.6.7
Requires-Dist: decorator==5.1.1
Requires-Dist: executing==1.2.0
Requires-Dist: ipykernel==6.23.1
Requires-Dist: ipython==8.13.2
Requires-Dist: jedi==0.18.2
Requires-Dist: jupyter_client==8.2.0
Requires-Dist: jupyter_core==5.3.0
Requires-Dist: matplotlib-inline==0.1.6
Requires-Dist: nest-asyncio==1.5.6
Requires-Dist: packaging==23.1
Requires-Dist: parso==0.8.3
Requires-Dist: pexpect==4.8.0
Requires-Dist: pickleshare==0.7.5
Requires-Dist: platformdirs==3.5.1
Requires-Dist: prompt-toolkit==3.0.38
Requires-Dist: psutil==5.9.5
Requires-Dist: ptyprocess==0.7.0
Requires-Dist: pure-eval==0.2.2
Requires-Dist: pyyaml==6.0.1
Requires-Dist: pycparser==2.21
Requires-Dist: Pygments==2.15.1
Requires-Dist: python-dateutil==2.8.2
Requires-Dist: python-dotenv>=1.0.0
Requires-Dist: pyzmq==26.0.3
Requires-Dist: six==1.16.0
Requires-Dist: stack-data==0.6.2
Requires-Dist: tornado==6.3.2
Requires-Dist: traitlets==5.9.0
Requires-Dist: watchdog==3.0.0
Requires-Dist: wcwidth==0.2.6
Requires-Dist: certifi==2023.7.22
Requires-Dist: charset-normalizer==3.2.0
Requires-Dist: idna==3.4
Requires-Dist: requests==2.31.0
Requires-Dist: urllib3==2.0.4
Requires-Dist: rich>=13.0.0
Requires-Dist: loguru>=0.7.0
Dynamic: author
Dynamic: classifier
Dynamic: description
Dynamic: description-content-type
Dynamic: home-page
Dynamic: license
Dynamic: license-file
Dynamic: requires-dist
Dynamic: summary
